[
  {
    "PayPeriodEndDate": "31-JAN-2019",
    "TiemSheetEntryId": 21,
    "TiemSheetEntryDate": "14-JAN-2019",
    "FirstName": "Dipti",
    "LastName": "Danial",
    "EmpCode": "EMP-114455",
    "title": "Is a dummy title",
    "logDate": "1-AUG-2019",
    "SyncDate": "14-JUL-2019",
    "ActivityCode": "ACT-001TEST",
    "Type": "timesheet_type",
    "Hours": 1.2,
    "Rate": 87.9,
    "Field_not_needed": "dummy"
  },
  {
    "PayPeriodEndDate": "31-JAN-2019",
    "TiemSheetEntryId": 22,
    "TiemSheetEntryDate": "14-JAN-2019",
    "FirstName": "Dipti",
    "LastName": "Danial",
    "EmpCode": "EMP-114455",
    "title": "Is a dummy title",
    "logDate": "1-AUG-2019",
    "SyncDate": "14-JUL-2019",
    "ActivityCode": "ACT-001TEST",
    "Type": "timesheet_type",
    "Hours": 1.3,
    "Rate": 87.9,
    "Field_not_needed": "dummy"
  },
  {
    "PayPeriodEndDate": "31-JAN-2019",
    "TiemSheetEntryId": 23,
    "TiemSheetEntryDate": "15-JAN-2019",
    "FirstName": "Dipti",
    "LastName": "Danial",
    "EmpCode": "EMP-114455",
    "title": "Is a dummy title",
    "logDate": "1-AUG-2019",
    "SyncDate": "14-JUL-2019",
    "ActivityCode": "ACT-001TEST",
    "Type": "timesheet_type",
    "Hours": 4,
    "Rate": 87.9,
    "Field_not_needed": "dummy"
  },
  {
    "PayPeriodEndDate": "31-JAN-2019",
    "TiemSheetEntryId": 60,
    "TiemSheetEntryDate": "15-JAN-2019",
    "FirstName": "sumano",
    "LastName": "Koli",
    "EmpCode": "EMP-7865",
    "title": "man not needed",
    "logDate": "1-AUG-2019",
    "SyncDate": "14-JUL-2019",
    "ActivityCode": "ACT-001TEST",
    "Type": "timesheet_type",
    "Hours": 1.5,
    "Rate": 102.5,
    "Field_not_needed": "dummy"
  }
]
